traceflow_win/__init__.py
traceflow_win/__main__.py
traceflow_win/traceflow_win.py
traceflow_win-1.0.3.dist-info/licenses/LICENSE
traceflow_win-1.0.3.dist-info/METADATA
traceflow_win-1.0.3.dist-info/WHEEL
traceflow_win-1.0.3.dist-info/entry_points.txt
traceflow_win-1.0.3.dist-info/top_level.txt
traceflow_win-1.0.3.dist-info/RECORD
