Metadata-Version: 2.4
Name: traceflow-win
Version: 1.0.3
Summary: A windows compatible path tracing package based off the functionality of rucarrol's traceflow.
Home-page: https://github.com/sshreve0/traceflow_win
Author: Salem Shreve
Author-email: salemshreve02@gmail.com
License: LICENSE
Classifier: Programming Language :: Python :: 3
Classifier: Operating System :: OS Independent
Requires-Python: >=3.10
License-File: LICENSE
Requires-Dist: dnspython>=2.7.0
Requires-Dist: scapy>=2.6.1
Dynamic: author
Dynamic: author-email
Dynamic: classifier
Dynamic: description
Dynamic: description-content-type
Dynamic: home-page
Dynamic: license
Dynamic: license-file
Dynamic: requires-dist
Dynamic: requires-python
Dynamic: summary
